{
  "validationRules": [],
  "transactionType": "VIEW RECORD",
  "tagKeys": "DEMO_-_VIEW_IP_NOTIFICATION;NEW_SECTION;",
  "status": "Complete",
  "sorting": [],
  "parentProcessNodes": [
    {
      "type": "TARGET",
      "referenceId": "a0Gf6000000EuXuEAK",
      "objectLabel": "Alerts",
      "objectAPIName": "SVMXC__SM_IB_Notification__c",
      "enableOnlineSearch": false,
      "allowImages": false,
      "allowAttachments": false
    }
  ],
  "pageLayoutDetails": {
    "type": "Header",
    "showProductHistory": false,
    "showAllSections": true,
    "showAccountHistory": false,
    "pageHeader": {
      "sections": [
        {
          "type": "Section",
          "sequence": 1,
          "referenceId": "a0cf60000003prQAAQ",
          "name": "New Section",
          "hideSectionTitle": false,
          "elements": [
            {
              "type": "REFERENCE",
              "sequence": 1,
              "row": 1,
              "required": false,
              "referenceToNameField": "SVMXC__Installed_Product__c.Name",
              "referenceTo": "SVMXC__Installed_Product__c",
              "referenceNameField": "Name",
              "readOnly": true,
              "overrideLookupContext": false,
              "lookupContextSource": "CURRENT_RECORD",
              "lookupConfiguration": {},
              "lkpSortDirection": "ASC",
              "isRichTextOnWeb": false,
              "events": [],
              "eltType": "Field",
              "column": 1,
              "apiName": "SVMXC__SM_Installed_Product__c",
              "allowNew": false
            },
            {
              "type": "PICKLIST",
              "sequence": 2,
              "row": 1,
              "required": false,
              "readOnly": false,
              "overrideLookupContext": false,
              "lookupContextSource": "CURRENT_RECORD",
              "lookupConfiguration": {},
              "lkpSortDirection": "ASC",
              "isRichTextOnWeb": false,
              "events": [],
              "eltType": "Field",
              "column": 2,
              "apiName": "SVMXC__SM_Status__c",
              "allowNew": false
            },
            {
              "type": "TEXTAREA",
              "sequence": 3,
              "row": 2,
              "required": false,
              "readOnly": false,
              "overrideLookupContext": false,
              "lookupContextSource": "CURRENT_RECORD",
              "lookupConfiguration": {},
              "lkpSortDirection": "ASC",
              "isRichTextOnWeb": false,
              "events": [],
              "eltType": "Field",
              "column": 1,
              "apiName": "SVMXC__SM_Description__c",
              "allowNew": false
            },
            {
              "type": "PICKLIST",
              "sequence": 4,
              "row": 2,
              "required": false,
              "readOnly": false,
              "overrideLookupContext": false,
              "lookupContextSource": "CURRENT_RECORD",
              "lookupConfiguration": {},
              "lkpSortDirection": "ASC",
              "isRichTextOnWeb": false,
              "events": [],
              "eltType": "Field",
              "column": 2,
              "apiName": "SVMXC__SM_Severity__c",
              "allowNew": false
            },
            {
              "type": "REFERENCE",
              "sequence": 5,
              "row": 3,
              "required": false,
              "referenceToNameField": "SVMXC__SM_Change_Order__c.Name",
              "referenceTo": "SVMXC__SM_Change_Order__c",
              "referenceNameField": "Name",
              "readOnly": false,
              "overrideLookupContext": false,
              "lookupContextSource": "CURRENT_RECORD",
              "lookupConfiguration": {},
              "lkpSortDirection": "ASC",
              "isRichTextOnWeb": false,
              "events": [],
              "eltType": "Field",
              "column": 1,
              "apiName": "SVMXC__SM_Change_Order__c",
              "allowNew": false
            },
            {
              "type": "REFERENCE",
              "sequence": 6,
              "row": 3,
              "required": false,
              "referenceToNameField": "SVMXC__SM_Change_Order_Line__c.Name",
              "referenceTo": "SVMXC__SM_Change_Order_Line__c",
              "referenceNameField": "Name",
              "readOnly": false,
              "overrideLookupContext": false,
              "lookupContextSource": "CURRENT_RECORD",
              "lookupConfiguration": {},
              "lkpSortDirection": "ASC",
              "isRichTextOnWeb": false,
              "events": [],
              "eltType": "Field",
              "column": 2,
              "apiName": "SVMXC__SM_Change_Order_Line__c",
              "allowNew": false
            }
          ],
          "columns": 2
        }
      ],
      "objectAPIName": "SVMXC__SM_IB_Notification__c"
    },
    "objectAPIName": "SVMXC__SM_IB_Notification__c",
    "name": "DEMO - View IP Notification",
    "lines": [],
    "isStandard": false,
    "includeSummary": false,
    "includeEventTimePlace": false,
    "includeContact": false,
    "hideSave": true,
    "hideQuickSave": true,
    "events": [],
    "enableTroubleShooting": false,
    "enableServiceReportView": false,
    "enableServiceReportGeneration": false,
    "dependencyExist": true
  },
  "name": "DEMO - View IP Notification",
  "linkedProcesses": [],
  "isStandard": false,
  "formulas": [],
  "events": [],
  "enableRealTimeValidation": true,
  "developerName": "SFM1674072222698263b52a125bd1a475ed1ad6a13bc3589",
  "childProcessNodes": [],
  "attachmentEnabled": false
}