{
  "validationRules": [],
  "transactionType": "SOURCE TO TARGET ALL",
  "tagKeys": "DEMO_-_CREATE_RMA_FROM_WORK_ORDER;SFM17180375804000A5086F8182403F87CABE72875A5E7DF_DESC;RMA_LINES;RMA_DETAILS;LOCATION;ADDRESS_DETAILS;",
  "syncMobileOption": "Default",
  "status": "Complete",
  "sorting": [],
  "parentProcessNodes": [
    {
      "type": "SOURCE",
      "referenceId": "a0Gf6000000EtztEAC",
      "objectAPIName": "SVMXC__Service_Order__c",
      "enableOnlineSearch": false,
      "allowImages": false,
      "allowAttachments": false
    },
    {
      "type": "TARGET",
      "sourceAPIName": "SVMXC__Service_Order__c",
      "referenceId": "a0Gf6000000EtzwEAC",
      "objectLabel": "Parts Order",
      "objectAPIName": "SVMXC__RMA_Shipment_Order__c",
      "mappingId": "MAP008-custom",
      "enableOnlineSearch": false,
      "allowImages": false,
      "allowAttachments": false
    }
  ],
  "pageLayoutDetails": {
    "type": "Header",
    "showProductHistory": false,
    "showAllSections": true,
    "showAccountHistory": false,
    "pageHeader": {
      "sections": [
        {
          "type": "Section",
          "sequence": 1,
          "referenceId": "a0cf60000003qncAAA",
          "name": "RMA Details",
          "hideSectionTitle": false,
          "elements": [
            {
              "type": "REFERENCE",
              "sequence": 1,
              "row": 1,
              "required": false,
              "referenceToNameField": "RecordType.Name",
              "referenceTo": "RecordType",
              "referenceNameField": "Name",
              "readOnly": true,
              "overrideLookupContext": false,
              "lookupContextSource": "CURRENT_RECORD",
              "lookupConfiguration": {},
              "lkpSortDirection": "ASC",
              "isRichTextOnWeb": false,
              "events": [],
              "eltType": "Field",
              "column": 1,
              "apiName": "RecordTypeId",
              "allowNew": false
            },
            {
              "type": "PICKLIST",
              "sequence": 2,
              "row": 1,
              "required": false,
              "readOnly": false,
              "overrideLookupContext": false,
              "lookupContextSource": "CURRENT_RECORD",
              "lookupConfiguration": {},
              "lkpSortDirection": "ASC",
              "isRichTextOnWeb": false,
              "events": [],
              "eltType": "Field",
              "column": 2,
              "apiName": "SVMXC__Order_Status__c",
              "allowNew": false
            },
            {
              "type": "REFERENCE",
              "sequence": 3,
              "row": 2,
              "required": false,
              "referenceToNameField": "Account.Name",
              "referenceTo": "Account",
              "referenceNameField": "Name",
              "readOnly": true,
              "overrideLookupContext": false,
              "lookupContextSource": "CURRENT_RECORD",
              "lookupConfiguration": {},
              "lkpSortDirection": "ASC",
              "isRichTextOnWeb": false,
              "events": [],
              "eltType": "Field",
              "column": 1,
              "apiName": "SVMXC__Company__c",
              "allowNew": false
            },
            {
              "type": "PICKLIST",
              "sequence": 4,
              "row": 2,
              "required": false,
              "readOnly": false,
              "overrideLookupContext": false,
              "lookupContextSource": "CURRENT_RECORD",
              "lookupConfiguration": {},
              "lkpSortDirection": "ASC",
              "isRichTextOnWeb": false,
              "events": [],
              "eltType": "Field",
              "column": 2,
              "apiName": "SVMXC__Priority__c",
              "allowNew": false
            },
            {
              "type": "PICKLIST",
              "sequence": 5,
              "row": 3,
              "required": false,
              "readOnly": true,
              "overrideLookupContext": false,
              "lookupContextSource": "CURRENT_RECORD",
              "lookupConfiguration": {},
              "lkpSortDirection": "ASC",
              "isRichTextOnWeb": false,
              "events": [],
              "eltType": "Field",
              "column": 1,
              "apiName": "SVMXC__Order_Type__c",
              "allowNew": false
            },
            {
              "type": "REFERENCE",
              "sequence": 6,
              "row": 3,
              "required": false,
              "referenceToNameField": "Account.Name",
              "referenceTo": "Account",
              "referenceNameField": "Name",
              "readOnly": false,
              "overrideLookupContext": false,
              "lookupContextSource": "CURRENT_RECORD",
              "lookupConfiguration": {
                "name": "DEMO: Couriers Only",
                "isStandard": false,
                "description": "Only filter for Couriers accounts",
                "lookupObject": "Account",
                "lookupFilter": {
                  "sourceObject": "Account",
                  "expressionsList": [
                    {
                      "sourceFldDtaType": "STRING",
                      "sourceField": "Name",
                      "sequence": 1,
                      "contextType": "Search",
                      "actionType": "Set Value"
                    },
                    {
                      "value": "Courier",
                      "sourceFldDtaType": "PICKLIST",
                      "sourceField": "Type",
                      "sequence": 1,
                      "parameterType": "Value",
                      "operator": "eq",
                      "operand": "Courier",
                      "actionType": "Set Value"
                    },
                    {
                      "sourceFldDtaType": "STRING",
                      "sourceField": "Name",
                      "sequence": 1,
                      "contextType": "Result",
                      "actionType": "Set Value"
                    },
                    {
                      "sourceFldDtaType": "STRING",
                      "sourceField": "BillingCity",
                      "sequence": 2,
                      "contextType": "Search",
                      "actionType": "Set Value"
                    },
                    {
                      "sourceFldDtaType": "STRING",
                      "sourceField": "BillingCity",
                      "sequence": 2,
                      "contextType": "Result",
                      "actionType": "Set Value"
                    },
                    {
                      "sourceFldDtaType": "STRING",
                      "sourceField": "BillingCountry",
                      "sequence": 3,
                      "contextType": "Result",
                      "actionType": "Set Value"
                    },
                    {
                      "sourceFldDtaType": "STRING",
                      "sourceField": "BillingCountry",
                      "sequence": 3,
                      "contextType": "Search",
                      "actionType": "Set Value"
                    },
                    {
                      "sourceFldDtaType": "BOOLEAN",
                      "sourceField": "Active__c",
                      "sequence": 4,
                      "contextType": "Result",
                      "actionType": "Set Value"
                    }
                  ],
                  "defaultOn": false,
                  "allowOverride": false
                },
                "lkpRecords": 50,
                "isDefault": false,
                "defaultColumn": "Name",
                "advancedFilters": []
              },
              "lookupConfigName": "DEMO: Couriers Only",
              "lkpSortDirection": "ASC",
              "isRichTextOnWeb": false,
              "events": [],
              "eltType": "Field",
              "column": 2,
              "apiName": "SVMXC__Shipping_Courier__c",
              "allowNew": false
            },
            {
              "type": "PICKLIST",
              "sequence": 7,
              "row": 4,
              "required": false,
              "readOnly": false,
              "overrideLookupContext": false,
              "lookupContextSource": "CURRENT_RECORD",
              "lookupConfiguration": {},
              "lkpSortDirection": "ASC",
              "isRichTextOnWeb": false,
              "events": [],
              "eltType": "Field",
              "column": 1,
              "apiName": "SVMXC__Billing_Type__c",
              "allowNew": false
            },
            {
              "type": "STRING",
              "sequence": 8,
              "row": 4,
              "required": false,
              "readOnly": false,
              "overrideLookupContext": false,
              "lookupContextSource": "CURRENT_RECORD",
              "lookupConfiguration": {},
              "lkpSortDirection": "ASC",
              "isRichTextOnWeb": false,
              "events": [],
              "eltType": "Field",
              "column": 2,
              "apiName": "SVMXC__Tracking_Number__c",
              "allowNew": false
            }
          ],
          "columns": 2
        },
        {
          "type": "Section",
          "sequence": 2,
          "referenceId": "a0cf60000003qndAAA",
          "name": "Location",
          "hideSectionTitle": false,
          "elements": [
            {
              "type": "PICKLIST",
              "sequence": 1,
              "row": 1,
              "required": false,
              "readOnly": false,
              "overrideLookupContext": false,
              "lookupContextSource": "CURRENT_RECORD",
              "lookupConfiguration": {},
              "lkpSortDirection": "ASC",
              "isRichTextOnWeb": false,
              "events": [],
              "eltType": "Field",
              "column": 1,
              "apiName": "SVMXC__Address_Type__c",
              "allowNew": false
            },
            {
              "type": "DATE",
              "sequence": 2,
              "row": 1,
              "required": false,
              "readOnly": false,
              "overrideLookupContext": false,
              "lookupContextSource": "CURRENT_RECORD",
              "lookupConfiguration": {},
              "lkpSortDirection": "ASC",
              "isRichTextOnWeb": false,
              "events": [],
              "eltType": "Field",
              "column": 2,
              "apiName": "SVMXC__Expected_Receive_Date__c",
              "allowNew": false
            },
            {
              "type": "REFERENCE",
              "sequence": 3,
              "row": 2,
              "required": false,
              "referenceToNameField": "SVMXC__Site__c.Name",
              "referenceTo": "SVMXC__Site__c",
              "referenceNameField": "Name",
              "readOnly": false,
              "overrideLookupContext": false,
              "lookupContextSource": "CURRENT_RECORD",
              "lookupConfiguration": {},
              "lkpSortDirection": "ASC",
              "isRichTextOnWeb": false,
              "formFillMappingName": "DEMO - From Location Address Complete",
              "formFillMappingDeveloperName": "MAP171811161755701fe485bbcda34b00863cd611a98ee1e",
              "events": [],
              "eltType": "Field",
              "column": 1,
              "apiName": "SVMXC__Source_Location__c",
              "allowNew": false
            },
            {
              "type": "REFERENCE",
              "sequence": 4,
              "row": 2,
              "required": false,
              "referenceToNameField": "SVMXC__Site__c.Name",
              "referenceTo": "SVMXC__Site__c",
              "referenceNameField": "Name",
              "readOnly": false,
              "overrideLookupContext": false,
              "lookupContextSource": "CURRENT_RECORD",
              "lookupConfiguration": {},
              "lkpSortDirection": "ASC",
              "isRichTextOnWeb": false,
              "formFillMappingName": "DEMO - To Location Address Complete",
              "formFillMappingDeveloperName": "MAP1718111567702e09804c90f8b746e023c71b2c4db030c",
              "events": [],
              "eltType": "Field",
              "column": 2,
              "apiName": "SVMXC__Destination_Location__c",
              "allowNew": false
            }
          ],
          "columns": 2
        },
        {
          "type": "Section",
          "sequence": 3,
          "referenceId": "a0cf60000003qneAAA",
          "name": "Address Details",
          "hideSectionTitle": false,
          "elements": [
            {
              "type": "TEXTAREA",
              "sequence": 1,
              "row": 1,
              "required": false,
              "readOnly": false,
              "overrideLookupContext": false,
              "lookupContextSource": "CURRENT_RECORD",
              "lookupConfiguration": {},
              "lkpSortDirection": "ASC",
              "isRichTextOnWeb": false,
              "events": [],
              "eltType": "Field",
              "column": 1,
              "apiName": "SVMXC__Source_Street__c",
              "allowNew": false
            },
            {
              "type": "TEXTAREA",
              "sequence": 2,
              "row": 1,
              "required": false,
              "readOnly": false,
              "overrideLookupContext": false,
              "lookupContextSource": "CURRENT_RECORD",
              "lookupConfiguration": {},
              "lkpSortDirection": "ASC",
              "isRichTextOnWeb": false,
              "events": [],
              "eltType": "Field",
              "column": 2,
              "apiName": "SVMXC__Destination_Street__c",
              "allowNew": false
            },
            {
              "type": "STRING",
              "sequence": 3,
              "row": 2,
              "required": false,
              "readOnly": false,
              "overrideLookupContext": false,
              "lookupContextSource": "CURRENT_RECORD",
              "lookupConfiguration": {},
              "lkpSortDirection": "ASC",
              "isRichTextOnWeb": false,
              "events": [],
              "eltType": "Field",
              "column": 1,
              "apiName": "SVMXC__Source_City__c",
              "allowNew": false
            },
            {
              "type": "STRING",
              "sequence": 4,
              "row": 2,
              "required": false,
              "readOnly": false,
              "overrideLookupContext": false,
              "lookupContextSource": "CURRENT_RECORD",
              "lookupConfiguration": {},
              "lkpSortDirection": "ASC",
              "isRichTextOnWeb": false,
              "events": [],
              "eltType": "Field",
              "column": 2,
              "apiName": "SVMXC__Destination_City__c",
              "allowNew": false
            },
            {
              "type": "STRING",
              "sequence": 5,
              "row": 3,
              "required": false,
              "readOnly": false,
              "overrideLookupContext": false,
              "lookupContextSource": "CURRENT_RECORD",
              "lookupConfiguration": {},
              "lkpSortDirection": "ASC",
              "isRichTextOnWeb": false,
              "events": [],
              "eltType": "Field",
              "column": 1,
              "apiName": "SVMXC__Source_State__c",
              "allowNew": false
            },
            {
              "type": "STRING",
              "sequence": 6,
              "row": 3,
              "required": false,
              "readOnly": false,
              "overrideLookupContext": false,
              "lookupContextSource": "CURRENT_RECORD",
              "lookupConfiguration": {},
              "lkpSortDirection": "ASC",
              "isRichTextOnWeb": false,
              "events": [],
              "eltType": "Field",
              "column": 2,
              "apiName": "SVMXC__Destination_State__c",
              "allowNew": false
            },
            {
              "type": "STRING",
              "sequence": 7,
              "row": 4,
              "required": false,
              "readOnly": false,
              "overrideLookupContext": false,
              "lookupContextSource": "CURRENT_RECORD",
              "lookupConfiguration": {},
              "lkpSortDirection": "ASC",
              "isRichTextOnWeb": false,
              "events": [],
              "eltType": "Field",
              "column": 1,
              "apiName": "SVMXC__Source_Zip__c",
              "allowNew": false
            },
            {
              "type": "STRING",
              "sequence": 8,
              "row": 4,
              "required": false,
              "readOnly": false,
              "overrideLookupContext": false,
              "lookupContextSource": "CURRENT_RECORD",
              "lookupConfiguration": {},
              "lkpSortDirection": "ASC",
              "isRichTextOnWeb": false,
              "events": [],
              "eltType": "Field",
              "column": 2,
              "apiName": "SVMXC__Destination_Zip__c",
              "allowNew": false
            },
            {
              "type": "PICKLIST",
              "sequence": 9,
              "row": 5,
              "required": false,
              "readOnly": false,
              "overrideLookupContext": false,
              "lookupContextSource": "CURRENT_RECORD",
              "lookupConfiguration": {},
              "lkpSortDirection": "ASC",
              "isRichTextOnWeb": false,
              "events": [],
              "eltType": "Field",
              "column": 1,
              "apiName": "SVMXC__Source_Country__c",
              "allowNew": false
            },
            {
              "type": "PICKLIST",
              "sequence": 10,
              "row": 5,
              "required": false,
              "readOnly": false,
              "overrideLookupContext": false,
              "lookupContextSource": "CURRENT_RECORD",
              "lookupConfiguration": {},
              "lkpSortDirection": "ASC",
              "isRichTextOnWeb": false,
              "events": [],
              "eltType": "Field",
              "column": 2,
              "apiName": "SVMXC__Destination_Country__c",
              "allowNew": false
            }
          ],
          "columns": 2
        },
        {
          "type": "Detail",
          "sequence": 1,
          "referenceId": "a0df6000000D5jLAAS",
          "objectAlias": "RMA Lines",
          "name": "RMA Lines",
          "columns": 1,
          "childAPIName": "SVMXC__RMA_Shipment_Line__c",
          "allowZeroLines": "Allow"
        }
      ],
      "objectAPIName": "SVMXC__RMA_Shipment_Order__c"
    },
    "objectAPIName": "SVMXC__RMA_Shipment_Order__c",
    "name": "DEMO - Create RMA from Work Order",
    "lines": [
      {
        "sequence": 1,
        "referenceId": "a0df6000000D5jLAAS",
        "objectAlias": "RMA Lines",
        "name": "RMA Lines",
        "hideEmptySection": false,
        "events": [],
        "elements": [
          {
            "type": "PICKLIST",
            "sequence": 5,
            "row": 5,
            "required": false,
            "readOnly": false,
            "overrideLookupContext": false,
            "lookupContextSource": "CURRENT_RECORD",
            "lookupConfiguration": {},
            "lkpSortDirection": "ASC",
            "isRichTextOnWeb": false,
            "events": [],
            "eltType": "Field",
            "column": 1,
            "apiName": "SVMXC__Disposition__c",
            "allowNew": false
          },
          {
            "type": "PICKLIST",
            "sequence": 4,
            "row": 4,
            "required": false,
            "readOnly": false,
            "overrideLookupContext": false,
            "lookupContextSource": "CURRENT_RECORD",
            "lookupConfiguration": {},
            "lkpSortDirection": "ASC",
            "isRichTextOnWeb": false,
            "events": [],
            "eltType": "Field",
            "column": 1,
            "apiName": "SVMXC__Expected_Condition__c",
            "allowNew": false
          },
          {
            "type": "DOUBLE",
            "sequence": 3,
            "row": 3,
            "required": false,
            "readOnly": false,
            "overrideLookupContext": false,
            "lookupContextSource": "CURRENT_RECORD",
            "lookupConfiguration": {},
            "lkpSortDirection": "ASC",
            "isRichTextOnWeb": false,
            "events": [],
            "eltType": "Field",
            "column": 1,
            "apiName": "SVMXC__Expected_Quantity2__c",
            "allowNew": false
          },
          {
            "type": "REFERENCE",
            "sequence": 2,
            "row": 2,
            "required": false,
            "referenceToNameField": "SVMXC__Installed_Product__c.Name",
            "referenceTo": "SVMXC__Installed_Product__c",
            "referenceNameField": "Name",
            "readOnly": false,
            "overrideLookupContext": false,
            "lookupContextSource": "CURRENT_RECORD",
            "lookupConfiguration": {},
            "lkpSortDirection": "ASC",
            "isRichTextOnWeb": false,
            "events": [],
            "eltType": "Field",
            "column": 1,
            "apiName": "SVMXC__Serial_Number__c",
            "allowNew": false
          },
          {
            "type": "REFERENCE",
            "sequence": 1,
            "row": 1,
            "required": false,
            "referenceToNameField": "Product2.Name",
            "referenceTo": "Product2",
            "referenceNameField": "Name",
            "readOnly": false,
            "overrideLookupContext": false,
            "lookupContextSource": "CURRENT_RECORD",
            "lookupConfiguration": {},
            "lkpSortDirection": "ASC",
            "isRichTextOnWeb": false,
            "events": [],
            "eltType": "Field",
            "column": 1,
            "apiName": "SVMXC__Product__c",
            "allowNew": false
          }
        ],
        "columns": 1,
        "childAPIName": "SVMXC__RMA_Shipment_Line__c",
        "allowZeroLines": "Allow",
        "allowNew": false,
        "allowDelete": false,
        "allowClone": true
      }
    ],
    "isStandard": false,
    "includeSummary": false,
    "includeEventTimePlace": false,
    "includeContact": false,
    "hideSave": false,
    "hideQuickSave": true,
    "events": [],
    "enableTroubleShooting": false,
    "enableServiceReportView": false,
    "enableServiceReportGeneration": false,
    "dependencyExist": true
  },
  "name": "DEMO - Create RMA from Work Order",
  "linkedProcesses": [],
  "isStandard": false,
  "formulas": [],
  "events": [],
  "enableRealTimeValidation": true,
  "developerName": "SFM17180375804000a5086f8182403f87cabe72875a5e7df",
  "description": "This SFM transaction is used to create a new RMA from a work order. Key information such as Account, Contact etc. are automatically copied to the RMA",
  "childProcessNodes": [
    {
      "type": "SOURCECHILD",
      "sequence": 1,
      "referenceId": "a0Gf6000000EtzuEAC",
      "parentColumnAPIName": "SVMXC__Service_Order__c",
      "objectAPIName": "SVMXC__Service_Order_Line__c",
      "nodeAPIName": "SVMXC__Service_Order__c",
      "enableOnlineSearch": false,
      "allowImages": false,
      "allowAttachments": false
    },
    {
      "type": "TARGETCHILD",
      "sourceAPIName": "SVMXC__Service_Order_Line__c",
      "sequence": 1,
      "referenceId": "a0Gf6000000Eu03EAC",
      "qualificationCriteriaId": "EXP17180373719902f84507ab2a77ebc0c8c7e678bb79a3e",
      "parentColumnAPIName": "SVMXC__RMA_Shipment_Order__c",
      "objectLabel": "RMA Lines",
      "objectAPIName": "SVMXC__RMA_Shipment_Line__c",
      "nodeAPIName": "SVMXC__RMA_Shipment_Order__c",
      "mappingId": "MAP171803843316754097f3029dbb7963a6475f0428997d7",
      "fieldMappingName": "DEMO - Work Order Lines to RMA Lines",
      "enableOnlineSearch": false,
      "allowImages": false,
      "allowAttachments": false
    }
  ],
  "attachmentEnabled": false
}